rfhub_static/__init__.py
rfhub_static/keyword_doc.py
rfhub_static/version.py
rfhub_static/static/favicon.ico
rfhub_static/static/css/bootstrap.min.css
rfhub_static/static/css/doc.css
rfhub_static/static/fonts/glyphicons-halflings-regular.eot
rfhub_static/static/fonts/glyphicons-halflings-regular.svg
rfhub_static/static/fonts/glyphicons-halflings-regular.ttf
rfhub_static/static/fonts/glyphicons-halflings-regular.woff
rfhub_static/static/js/bootstrap.min.js
rfhub_static/static/js/doc.js
rfhub_static/static/js/jquery.min.js
rfhub_static/templates/base.html
rfhub_static/templates/twocolumn.html
robotframework_hub_static-1.0.3.dist-info/licenses/LICENSE
robotframework_hub_static-1.0.3.dist-info/METADATA
robotframework_hub_static-1.0.3.dist-info/WHEEL
robotframework_hub_static-1.0.3.dist-info/entry_points.txt
robotframework_hub_static-1.0.3.dist-info/top_level.txt
robotframework_hub_static-1.0.3.dist-info/zip-safe
robotframework_hub_static-1.0.3.dist-info/RECORD
