Metadata-Version: 2.4
Name: robotframework-hub-static
Version: 1.0.3
Summary: Create robot keyword documentation as static HTML
Home-page: https://github.com/bli74/robotframework-hub/
Author: Bryan Oakley
Author-email: Bryan Oakley <bryan.oakley@gmail.com>
Maintainer: Bert Lindemann
Maintainer-email: Bert Lindemann <bert.lindemann@gmail.com>
License: Apache License 2.0
Project-URL: Homepage, https://github.com/bli74/robotframework-hub-static
Project-URL: Repository, https://github.com/bli74/robotframework-hub-static
Project-URL: Issues, https://github.com/bli74/robotframework-hub-static/issues
Keywords: robotframework
Classifier: Development Status :: 5 - Production/Stable
Classifier: License :: OSI Approved :: Apache Software License
Classifier: Operating System :: OS Independent
Classifier: Framework :: Robot Framework
Classifier: Programming Language :: Python :: 3
Classifier: Programming Language :: Python :: 3.8
Classifier: Programming Language :: Python :: 3.9
Classifier: Programming Language :: Python :: 3.10
Classifier: Programming Language :: Python :: 3.11
Classifier: Programming Language :: Python :: 3.12
Classifier: Topic :: Software Development :: Testing
Classifier: Topic :: Software Development :: Quality Assurance
Classifier: Intended Audience :: Developers
Requires-Python: >=3.8
License-File: LICENSE
Requires-Dist: Jinja2>=3.0.0
Requires-Dist: robotframework>=2.8.5
Provides-Extra: test
Requires-Dist: robotframework-requests; extra == "test"
Dynamic: author
Dynamic: home-page
Dynamic: license-file
Dynamic: maintainer
Dynamic: requires-python
